domdf_sphinx_theme/static/css/domdf_sphinx_theme.css
domdf_sphinx_theme/static/js/theme.js
domdf_sphinx_theme/__init__.py
domdf_sphinx_theme/footer.html
domdf_sphinx_theme/layout.html
domdf_sphinx_theme/theme.conf
domdf_sphinx_theme/versions.html
domdf_sphinx_theme-24.1.1.dist-info/LICENSE
domdf_sphinx_theme-24.1.1.dist-info/METADATA
domdf_sphinx_theme-24.1.1.dist-info/WHEEL
domdf_sphinx_theme-24.1.1.dist-info/entry_points.txt
domdf_sphinx_theme-24.1.1.dist-info/RECORD
