Metadata-Version: 2.2
Name: domdf-sphinx-theme
Version: 24.1.1
Summary: Customised 'sphinx_rtd_theme' used by my Python projects.
Author-email: Dominic Davis-Foster <dominic@davis-foster.co.uk>
License: MIT
Keywords: documentation,sphinx,sphinx-theme
Home-page: https://github.com/domdfcoding/domdf_sphinx_theme
Project-URL: Issue Tracker, https://github.com/domdfcoding/domdf_sphinx_theme/issues
Project-URL: Source Code, https://github.com/domdfcoding/domdf_sphinx_theme
Project-URL: Documentation, https://domdf-sphinx-theme.readthedocs.io/en/latest
Platform: Windows
Platform: macOS
Platform: Linux
Classifier: Development Status :: 4 - Beta
Classifier: Environment :: Web Environment
Classifier: Framework :: Sphinx
Classifier: Framework :: Sphinx :: Extension
Classifier: Framework :: Sphinx :: Theme
Classifier: Intended Audience :: Developers
Classifier: License :: OSI Approved :: MIT License
Classifier: Operating System :: OS Independent
Classifier: Programming Language :: JavaScript
Classifier: Programming Language :: Python
Classifier: Programming Language :: Python :: 3 :: Only
Classifier: Programming Language :: Python :: 3.6
Classifier: Programming Language :: Python :: 3.7
Classifier: Programming Language :: Python :: 3.8
Classifier: Programming Language :: Python :: 3.9
Classifier: Programming Language :: Python :: Implementation :: CPython
Classifier: Topic :: Documentation
Classifier: Topic :: Documentation :: Sphinx
Classifier: Topic :: Software Development :: Documentation
Classifier: Topic :: Software Development :: Libraries :: Python Modules
Classifier: Topic :: Utilities
Requires-Python: >=3.6
Requires-Dist: docutils>=0.16
Requires-Dist: sphinx>=3.0.4
Requires-Dist: sphinx-rtd-theme<1.1,>0.4
Requires-Dist: sphinxcontrib-jquery>=4.1
